[{"id": "405310d7-8e3a-4bf1-a6fa-e51f7d3731bb", "updated_at": "2023-01-15T14:36:36", "last_name": "Ada", "email": "adaabigail@gmail.com", "phone_no": "09075635274", "com_res": "Evidence", "first_name": "Abigail", "created_at": "2023-01-15T14:19:03", "password": "ada.ada", "user_type": "regular", "__class__": "User"}, {"id": "57277f95-50e5-48ff-b44a-44c18dcfa54f", "updated_at": "2023-01-14T16:48:28", "last_name": "Bashir", "email": "halimabashir@gmail.com", "phone_no": "07045362718", "com_res": null, "first_name": "Halimat", "created_at": "2023-01-14T16:48:28", "password": "Mathsqueen", "user_type": "regular", "__class__": "User"}, {"id": "69729270-e351-4a17-a96b-6d58914915c2", "updated_at": "2023-01-15T05:00:13", "last_name": "Abubakar", "email": "aminaabubaka@gmail.com", "phone_no": "08052413689", "com_res": "Osasoghie", "first_name": "Amina", "created_at": "2023-01-15T04:59:22", "password": "aminatu", "user_type": "regular", "__class__": "User"}, {"id": "6b138e79-6305-4d9f-a3ec-009dd8aa904f", "updated_at": "2023-01-12T07:24:40", "last_name": "Akanbi", "email": "successakanbi@gmail.com", "phone_no": "07054638534", "com_res": null, "first_name": "Success", "created_at": "2023-01-12T07:19:56", "password": "successakanbis", "user_type": "vendor", "__class__": "User"}, {"id": "72b2937c-8cfc-4aa5-b3ab-0c209896e85c", "updated_at": "2023-01-14T16:37:22", "last_name": "Ikwuegbu", "email": "onyekaikwegbu@gmail.com", "phone_no": "08056382548", "com_res": "Adolor", "first_name": "Onyeka", "created_at": "2023-01-14T16:34:32", "password": "Tizzyshaun", "user_type": "agent", "__class__": "User"}, {"id": "9512f5c2-8e76-42b5-9a3a-421bc8843613", "updated_at": "2023-01-15T00:57:15", "last_name": "Charles", "email": "okaforcharles@gmail.com", "phone_no": "08034563164", "com_res": "Oluku", "first_name": "Okafor", "created_at": "2023-01-12T12:38:47", "password": "charleboy", "user_type": "agent", "__class__": "User"}, {"id": "9ae61827-03a8-4fd1-8b48-122e0c3a6842", "updated_at": "2023-01-16T11:56:51", "last_name": "Akanbi ", "email": "justin.hunter.jade@gmail.com", "phone_no": "07054598108", "com_res": "Ekosodin", "first_name": "Success ", "created_at": "2023-01-16T11:56:06", "password": "y9RJs2rnHgMHwG3", "user_type": "agent", "__class__": "User"}, {"id": "9f441195-d730-4599-a07e-eb618493649d", "updated_at": "2023-01-13T22:51:18", "last_name": "Olubukola", "email": "timileyinolubukola@gmail.com", "phone_no": "08056483527", "com_res": "Evidence", "first_name": "Timileyin", "created_at": "2023-01-13T22:50:57", "password": "Olubuks123", "user_type": "sp", "__class__": "User"}, {"id": "ac1cd81f-b70b-4cb0-90b5-754c8a8caae7", "updated_at": "2023-01-13T22:49:12", "last_name": "Ike", "email": "ikerosemary@gmail.com", "phone_no": "09045653242", "com_res": "Oluku", "first_name": "Rosemary", "created_at": "2023-01-13T22:48:54", "password": "Hottestgirl", "user_type": "agent", "__class__": "User"}, {"id": "b9e8a5f2-53bf-46af-a99b-d3dcb856c1ab", "updated_at": "2023-01-12T07:16:10", "last_name": "Akinwonjowo", "email": "Akinwonjowodennisco@gmail.com", "phone_no": "09035371162", "com_res": "Ekosodin", "first_name": "Dennis", "created_at": "2023-01-12T07:09:42", "password": "focus123", "user_type": "regular", "__class__": "User"}, {"id": "cde4ae16-88f2-405e-a7d6-f403ed71611d", "updated_at": "2023-01-15T06:22:02", "last_name": "akanbi", "email": "successakanbiosoname@gmail.com", "phone_no": "07037170954", "com_res": "EDPA", "first_name": "success", "created_at": "2023-01-15T06:21:29", "password": "6ygudgaggDtfayfe7%^R\u00a3", "user_type": "regular", "__class__": "User"}, {"id": "d0238401-2492-4721-ab19-6205a5eee545", "updated_at": "2023-01-15T14:43:38", "last_name": "Adekola", "email": "kingsleyadekola@gmail.com", "phone_no": "08047583826", "com_res": "Ekosodin", "first_name": "Kingsley", "created_at": "2023-01-13T20:36:08", "password": "paparazzi", "user_type": "agent", "__class__": "User"}, {"id": "ed58bbdd-7ee3-4d81-82ad-432a3901e8f9", "updated_at": "2023-01-12T19:09:08", "last_name": "Ajirireloja", "email": "emmaajirire@gmail.com", "phone_no": "07042162986", "com_res": "Osasoghie", "first_name": "Emmanuel ", "created_at": "2023-01-12T19:07:42", "password": "shortmandev", "user_type": "vendor", "__class__": "User"}, {"id": "f60b514e-7219-4dd0-bf5d-5e604535c6cb", "updated_at": "2023-01-16T00:39:04", "last_name": "Momoh", "email": "happinessmomoh@gmail.com", "phone_no": "08056483527", "com_res": "Ring Road", "first_name": "Happiness", "created_at": "2023-01-16T00:38:32", "password": "happiness243", "user_type": "sp", "__class__": "User"}, {"id": "f742ed94-f20d-4319-86ed-4e20da8b854e", "updated_at": "2023-01-14T13:16:10", "last_name": "Iwezue", "email": "iwezuedaniel@gmail.com", "phone_no": "08051236584", "com_res": "Adolor", "first_name": "Daniel", "created_at": "2023-01-14T13:14:55", "password": "rakifi258", "user_type": "vendor", "__class__": "User"}, {"updated_at": "2023-01-16T17:46:30", "id": "01cfdab9-7c31-4876-95e4-4d232d042f29", "colour": "yellow", "available": null, "apartment": "Self-contain", "street_id": "e13254c3-23c8-45bb-a1c0-bdb3e19bab86", "owner_id": "ac1cd81f-b70b-4cb0-90b5-754c8a8caae7", "price": 100000, "created_at": "2023-01-16T17:45:00", "storey": 5, "name": "City gate hostel", "description": null, "__class__": "House"}, {"updated_at": "2023-01-14T15:56:12", "id": "028b6090-fa5d-4ba7-9190-d1f730db8ad2", "colour": "gray", "available": null, "apartment": "One-bedroom", "street_id": "8fd6243d-a315-4ca0-81b4-6d634f29b43a", "owner_id": "ac1cd81f-b70b-4cb0-90b5-754c8a8caae7", "price": 140000, "created_at": "2023-01-14T15:55:18", "storey": 5, "name": "Happiness hostel", "description": null, "__class__": "House"}, {"updated_at": "2023-01-13T22:32:39", "id": "13316c94-7ab6-455d-82b3-aadf564f9622", "colour": null, "available": null, "apartment": "One-bedroom", "street_id": "defd8f54-2f9b-4730-96e3-30ed7a08fafe", "owner_id": "d0238401-2492-4721-ab19-6205a5eee545", "price": 120000, "created_at": "2023-01-13T22:31:45", "storey": 1, "name": "Sun-city hostel", "description": null, "__class__": "House"}, {"updated_at": "2023-01-13T20:41:15", "id": "41b6ce63-a225-4057-82eb-385a4864032d", "colour": "Brown", "available": null, "apartment": "Two-bedroom", "street_id": "6eac33e8-f2d5-431f-aa22-9f3af77ec844", "owner_id": "9512f5c2-8e76-42b5-9a3a-421bc8843613", "price": 320000, "created_at": "2023-01-13T20:41:15", "storey": 2, "name": "Iyayi hostel", "description": null, "__class__": "House"}, {"updated_at": "2023-01-13T21:11:54", "id": "531e39df-e997-4266-ba91-51e92d514d42", "colour": "Blue", "available": null, "apartment": "Single-room", "street_id": "e13254c3-23c8-45bb-a1c0-bdb3e19bab86", "owner_id": "9512f5c2-8e76-42b5-9a3a-421bc8843613", "price": 60000, "created_at": "2023-01-13T21:11:54", "storey": 2, "name": "God's grace hostel", "description": null, "__class__": "House"}, {"updated_at": "2023-01-12T13:55:46", "id": "734fe00d-fe18-4708-a110-e42457f5a45d", "colour": "white", "available": null, "apartment": "Self-contain", "street_id": "8fd6243d-a315-4ca0-81b4-6d634f29b43a", "owner_id": "9512f5c2-8e76-42b5-9a3a-421bc8843613", "price": 120000, "created_at": "2023-01-12T12:39:05", "storey": 3, "name": "Whitegate hostel", "description": null, "__class__": "House"}, {"updated_at": "2023-01-13T20:37:34", "id": "8693da0a-3362-45cc-b17c-8c57f2a518f4", "colour": "Yellow", "available": null, "apartment": "One-bedroom", "street_id": "defd8f54-2f9b-4730-96e3-30ed7a08fafe", "owner_id": "d0238401-2492-4721-ab19-6205a5eee545", "price": 180000, "created_at": "2023-01-13T20:37:34", "storey": 3, "name": "Mama villa", "description": null, "__class__": "House"}, {"updated_at": "2023-01-13T20:39:24", "id": "9462fd3c-e1be-479b-9f83-6367d79b30e7", "colour": "Green", "available": null, "apartment": "Self-contain", "street_id": "8fd6243d-a315-4ca0-81b4-6d634f29b43a", "owner_id": "d0238401-2492-4721-ab19-6205a5eee545", "price": 200000, "created_at": "2023-01-13T20:39:24", "storey": 1, "name": "Obama hostel", "description": null, "__class__": "House"}, {"updated_at": "2023-01-12T14:01:00", "id": "b678ac6c-1956-45c7-baa3-ecd2563cf1cf", "colour": "Green", "available": null, "apartment": "Self-contain", "street_id": "5e7db162-7bb7-4729-a1aa-c0efa9a297de", "owner_id": "9512f5c2-8e76-42b5-9a3a-421bc8843613", "price": 75000, "created_at": "2023-01-12T13:59:30", "storey": 2, "name": "Greenville hostel", "description": null, "__class__": "House"}, {"updated_at": "2023-01-13T21:13:34", "id": "ce5a115d-957d-4dbd-80cf-e465e3afaa3b", "colour": "Yellow", "available": null, "apartment": "Single-room", "street_id": "e13254c3-23c8-45bb-a1c0-bdb3e19bab86", "owner_id": "9512f5c2-8e76-42b5-9a3a-421bc8843613", "price": 72000, "created_at": "2023-01-13T21:13:34", "storey": 3, "name": "Twins hostel", "description": null, "__class__": "House"}, {"updated_at": "2023-01-13T20:30:52", "id": "dc7fe320-35d8-4dd2-b265-78b30bf3cc91", "colour": "Brown", "available": null, "apartment": "Single-room", "street_id": "e13254c3-23c8-45bb-a1c0-bdb3e19bab86", "owner_id": "9512f5c2-8e76-42b5-9a3a-421bc8843613", "price": 65000, "created_at": "2023-01-13T20:30:52", "storey": 2, "name": "Ikpadonmon villa", "description": null, "__class__": "House"}, {"updated_at": "2023-01-14T22:54:57", "created_at": "2023-01-14T22:54:57", "name": "Evidence", "id": "01f462c7-2dcb-4a61-b7a3-5632492d2b16", "__class__": "Environment"}, {"updated_at": "2023-01-14T22:55:43", "created_at": "2023-01-14T22:55:43", "name": "Oluku", "id": "243bde00-ea11-4863-b135-5ae01f60883f", "__class__": "Environment"}, {"updated_at": "2023-01-12T12:35:26", "created_at": "2023-01-12T12:35:26", "name": "Osasoghie", "id": "7cb2138e-5b99-4418-ad0c-b2facb1a72e3", "__class__": "Environment"}, {"updated_at": "2023-01-15T13:23:02", "created_at": "2023-01-15T13:23:02", "name": "Ebvoumore", "id": "8e563cbb-e6f6-4517-9c43-3d43fd2c0f04", "__class__": "Environment"}, {"updated_at": "2023-01-12T12:35:19", "created_at": "2023-01-12T12:35:19", "name": "BDPA", "id": "93e7416c-a1b2-4023-b35e-ec5fc8c309a6", "__class__": "Environment"}, {"updated_at": "2023-01-12T12:35:13", "created_at": "2023-01-12T12:35:13", "name": "Adolor", "id": "9820c31c-3b98-46b6-a3af-f24b1015a261", "__class__": "Environment"}, {"updated_at": "2023-01-12T12:35:57", "created_at": "2023-01-12T12:35:57", "name": "Ring Road", "id": "c891618c-343a-481a-87c6-328299c86c46", "__class__": "Environment"}, {"updated_at": "2023-01-12T12:35:47", "created_at": "2023-01-12T12:35:47", "name": "Isihor", "id": "ce7c281a-8fbf-4d74-9349-54d6d300e45b", "__class__": "Environment"}, {"updated_at": "2023-01-12T12:35:38", "created_at": "2023-01-12T12:35:38", "name": "Uselu", "id": "d19a96eb-e0c7-4198-a83f-ffc35d77a6ec", "__class__": "Environment"}, {"updated_at": "2023-01-12T12:35:03", "created_at": "2023-01-12T12:35:03", "name": "Ekosodin", "id": "fd2db91d-dc14-47d2-9594-e5a6585055c5", "__class__": "Environment"}, {"created_at": "2023-01-12T13:54:33", "env_id": "fd2db91d-dc14-47d2-9594-e5a6585055c5", "name": "Newton", "updated_at": "2023-01-12T13:54:33", "id": "5e7db162-7bb7-4729-a1aa-c0efa9a297de", "__class__": "Street"}, {"created_at": "2023-01-12T13:53:18", "env_id": "93e7416c-a1b2-4023-b35e-ec5fc8c309a6", "name": "19th", "updated_at": "2023-01-12T13:53:18", "id": "6eac33e8-f2d5-431f-aa22-9f3af77ec844", "__class__": "Street"}, {"created_at": "2023-01-12T13:53:33", "env_id": "93e7416c-a1b2-4023-b35e-ec5fc8c309a6", "name": "21st", "updated_at": "2023-01-12T13:53:33", "id": "8fd6243d-a315-4ca0-81b4-6d634f29b43a", "__class__": "Street"}, {"created_at": "2023-01-12T13:53:58", "env_id": "fd2db91d-dc14-47d2-9594-e5a6585055c5", "name": "Edo", "updated_at": "2023-01-12T13:53:58", "id": "defd8f54-2f9b-4730-96e3-30ed7a08fafe", "__class__": "Street"}, {"created_at": "2023-01-12T13:55:03", "env_id": "7cb2138e-5b99-4418-ad0c-b2facb1a72e3", "name": "Holy Rosary", "updated_at": "2023-01-12T13:55:03", "id": "e13254c3-23c8-45bb-a1c0-bdb3e19bab86", "__class__": "Street"}, {"created_at": "2023-01-12T13:52:27", "env_id": "7cb2138e-5b99-4418-ad0c-b2facb1a72e3", "name": "Image", "updated_at": "2023-01-12T13:52:27", "id": "f0667ccc-d997-451f-a250-89a7f4188824", "__class__": "Street"}]
